{
  "project_info": {
    "project_number": "628326232322",
    "project_id": "famlicious-d7c8f",
    "storage_bucket": "famlicious-d7c8f.appspot.com"
  },
  "client": [
    {
      "client_info": {
        "mobilesdk_app_id": "1:628326232322:android:9b59a204617ddf5a72921b",
        "android_client_info": {
          "package_name": "com.example.famlicious_app"
        }
      },
      "oauth_client": [
        {
          "client_id": "628326232322-s7r1vdp3rlgr6h6ecoba67a0694kh408.apps.googleusercontent.com",
          "client_type": 1,
          "android_info": {
            "package_name": "com.example.famlicious_app",
            "certificate_hash": "27a0a93f9977d7081da1798d84f1b810773be554"
          }
        },
        {
          "client_id": "628326232322-k4vpnluairlhpco6n9lbpphkogh3a37t.apps.googleusercontent.com",
          "client_type": 3
        }
      ],
      "api_key": [
        {
          "current_key": "AIzaSyCj9PzsTNRBXRQfDbRkn_3LQ1IovKwZQ7A"
        }
      ],
      "services": {
        "appinvite_service": {
          "other_platform_oauth_client": [
            {
              "client_id": "628326232322-k4vpnluairlhpco6n9lbpphkogh3a37t.apps.googleusercontent.com",
              "client_type": 3
            }
          ]
        }
      }
    }
  ],
  "configuration_version": "1"
}